lheutils/__init__.py
lheutils/_version.py
lheutils/_version.pyi
lheutils/cli/lhe2lhe.py
lheutils/cli/lhecheck.py
lheutils/cli/lhediff.py
lheutils/cli/lhefilter.py
lheutils/cli/lheinfo.py
lheutils/cli/lhemerge.py
lheutils/cli/lheshow.py
lheutils/cli/lhesplit.py
lheutils/cli/lhestack.py
lheutils/cli/lheunstack.py
lheutils/cli/util.py
lheutils-0.0.3.dist-info/METADATA
lheutils-0.0.3.dist-info/WHEEL
lheutils-0.0.3.dist-info/entry_points.txt
lheutils-0.0.3.dist-info/licenses/LICENSE
lheutils-0.0.3.dist-info/RECORD
